{"auditid":"0","label":"","text":"<div id=\"Isa.12\" class=\"chapter\">\n<h3 class=\"s1\">Louange au Dieu sauveur<\/h3>\n<p class=\"q1\"><span class=\"v23_12_1\"><sup id=\"Isa.12.1\" class=\"v23_12_1\">1<\/sup>Peuple lib\u00e9r\u00e9, tu diras ce jour-l\u00e0 :<\/span><\/p>\n<p class=\"q1\"><span class=\"v23_12_1\">\u00ab Seigneur, je veux te louer ;<\/span><\/p>\n<p class=\"q1\"><span class=\"v23_12_1\">j\u2019avais m\u00e9rit\u00e9 ta col\u00e8re,<\/span><\/p>\n<p class=\"q1\"><span class=\"v23_12_1\">mais tu ne m\u2019en veux plus,<\/span><\/p>\n<p class=\"q1\"><span class=\"v23_12_1\">tu m\u2019as r\u00e9confort\u00e9.<\/span><\/p>\n<p class=\"b\"><\/p>\n<p class=\"q1\"><span class=\"v23_12_2\"><sup id=\"Isa.12.2\" class=\"v23_12_2\">2<\/sup>Voici le Dieu qui m\u2019a sauv\u00e9 ;<\/span><\/p>\n<p class=\"q1\"><span class=\"v23_12_2\">je me sens en s\u00e9curit\u00e9, je n\u2019ai plus peur.<\/span><\/p>\n<p class=\"q1\"><span class=\"v23_12_2\">Ma grande force, c\u2019est le Seigneur ;<\/span><\/p>\n<p class=\"q1\"><span class=\"v23_12_2\">il est mon sauveur. \u00bb<\/span><\/p>\n<p class=\"q1\"><span class=\"v23_12_3\"><sup id=\"Isa.12.3\" class=\"v23_12_3\">3<\/sup>Avec joie vous puiserez<\/span><\/p>\n<p class=\"q1\"><span class=\"v23_12_3\">aux sources du salut.<\/span><\/p>\n<p class=\"b\"><\/p>\n<p class=\"q1\"><span class=\"v23_12_4\"><sup id=\"Isa.12.4\" class=\"v23_12_4\">4<\/sup>Ce jour-l\u00e0, vous direz :<\/span><\/p>\n<p class=\"q1\"><span class=\"v23_12_4\">\u00ab Louez le Seigneur,<\/span><\/p>\n<p class=\"q1\"><span class=\"v23_12_4\">dites bien haut qui est Dieu,<\/span><\/p>\n<p class=\"q1\"><span class=\"v23_12_4\">annoncez \u00e0 tout le monde<\/span><\/p>\n<p class=\"q1\"><span class=\"v23_12_4\">quels sont ses exploits,<\/span><\/p>\n<p class=\"q1\"><span class=\"v23_12_4\">rappelez \u00e0 tous<\/span><\/p>\n<p class=\"q1\"><span class=\"v23_12_4\">quel grand nom est le sien.<\/span><\/p>\n<p class=\"q1\"><span class=\"v23_12_5\"><sup id=\"Isa.12.5\" class=\"v23_12_5\">5<\/sup>C\u00e9l\u00e9brez le Seigneur par vos chants,<\/span><\/p>\n<p class=\"q1\"><span class=\"v23_12_5\">car il a fait de grandes choses.<\/span><\/p>\n<p class=\"q1\"><span class=\"v23_12_5\">Qu\u2019on les fasse conna\u00eetre<\/span><\/p>\n<p class=\"q1\"><span class=\"v23_12_5\">dans le monde entier ! \u00bb<\/span><\/p>\n<p class=\"q1\"><span class=\"v23_12_6\"><sup id=\"Isa.12.6\" class=\"v23_12_6\">6<\/sup>Population de Sion, manifeste ta joie,<\/span><\/p>\n<p class=\"q1\"><span class=\"v23_12_6\">pousse des cris d\u2019enthousiasme,<\/span><\/p>\n<p class=\"q1\"><span class=\"v23_12_6\">car il est grand,<\/span><\/p>\n<p class=\"q1\"><span class=\"v23_12_6\">celui qui est chez toi,<\/span><\/p>\n<p class=\"q1\"><span class=\"v23_12_6\">l\u2019unique vrai Dieu, le Dieu d\u2019Isra\u00ebl.<\/span><\/p>\n<p class=\"b\"><\/p>\n<h3 class=\"ms2\">\u2013\u2013\u2013\u2013\u2013<\/h3>\n<\/div>\n","chapter":"12","id":"fra-FRC97:Isa.12","osis_end":"fra-FRC97:Isa.12.6","order":"23012","link":"fra-FRC97\/Isa\/12","display":"\u00c9sa\u00efe 12","book":{"version_id":"232","name":"\u00c9sa\u00efe","abbr":"Isa","ord":"23","book_group_id":"0","testament":"OT","id":"fra-FRC97:Isa","osis_end":"fra-FRC97:Isa.66.24"},"version":{"auditid":"0","display_abbreviation":"FRC97","version":"fra-FRC97","id":"fra-FRC97","name":"La Bible en fran\u00e7ais courant","short_desc":null,"description":null,"active":1,"active_api":0,"listed":1,"orderindex":"99","lang":"fra","lang_code":"ISO 639-3","copyright":"<p>Copyright &#169; 1997, Soci&#233;t&#233; biblique fran&#231;aise. Avec autorisation. Tous droits r&#233;serv&#233;s.<\/p>","contact_url":"http:\/\/www.la-bible.net\/","audio":"NONE","sections":[{"version_id":"fra-FRC97","id":"OT","name":"Old Testament"},{"version_id":"fra-FRC97","id":"NT","name":"New Testament"}]},"audio":null,"prevChapterId":"fra-FRC97:Isa.11","nextChapterId":"fra-FRC97:Isa.13","nextChapter":{"auditid":"0","label":"","text":"<div id=\"Isa.13\" class=\"chapter\">\n<h3 class=\"s1\">La fin de Babylone<\/h3>\n<p class=\"p\"><span class=\"v23_13_1\"><sup id=\"Isa.13.1\" class=\"v23_13_1\">1<\/sup>Message qu\u2019\u00c9sa\u00efe, fils d\u2019Amots re\u00e7ut du Seigneur ; il est intitul\u00e9 \u201cBabylone\u201d :<\/span><\/p>\n<p class=\"q1\"><span class=\"v23_13_2\"><sup id=\"Isa.13.2\" class=\"v23_13_2\">2<\/sup>\u00ab Sur une montagne d\u00e9nud\u00e9e,<\/span><\/p>\n<p class=\"q1\"><span class=\"v23_13_2\">dressez un signal, dit le Seigneur.<\/span><\/p>\n<p class=\"q1\"><span class=\"v23_13_2\">Avertissez \u00e0 grands cris les guerriers.<\/span><\/p>\n<p class=\"q1\"><span class=\"v23_13_2\">Faites-leur signe de la main, qu\u2019ils entrent<\/span><\/p>\n<p class=\"q1\"><span class=\"v23_13_2\">par les portes des volontaires !<\/span><\/p>\n<p class=\"q1\"><span class=\"v23_13_3\"><sup id=\"Isa.13.3\" class=\"v23_13_3\">3<\/sup>Je commande moi-m\u00eame<\/span><\/p>\n<p class=\"q1\"><span class=\"v23_13_3\">aux hommes qui me sont consacr\u00e9s,<\/span><\/p>\n<p class=\"q1\"><span class=\"v23_13_3\">j\u2019ai convoqu\u00e9 mes soldats d\u2019\u00e9lite,<\/span><\/p>\n<p class=\"q1\"><span class=\"v23_13_3\">les joyeux champions de mon honneur,<\/span><\/p>\n<p class=\"q1\"><span class=\"v23_13_3\">pour manifester ma col\u00e8re. \u00bb<\/span><\/p>\n<p class=\"b\"><\/p>\n<p class=\"q1\"><span class=\"v23_13_4\"><sup id=\"Isa.13.4\" class=\"v23_13_4\">4<\/sup>\u00c9coutez ce bruit sur les montagnes :<\/span><\/p>\n<p class=\"q1\"><span class=\"v23_13_4\">on dirait une foule immense.<\/span><\/p>\n<p class=\"q1\"><span class=\"v23_13_4\">\u00c9coutez ce grondement de royaumes,<\/span><\/p>\n<p class=\"q1\"><span class=\"v23_13_4\">de nations rassembl\u00e9es.<\/span><\/p>\n<p class=\"q1\"><span class=\"v23_13_4\">Le Seigneur de l\u2019univers<\/span><\/p>\n<p class=\"q1\"><span class=\"v23_13_4\">passe en revue l\u2019arm\u00e9e qui va combattre.<\/span><\/p>\n<p class=\"q1\"><span class=\"v23_13_5\"><sup id=\"Isa.13.5\" class=\"v23_13_5\">5<\/sup>Ils arrivent d\u2019un pays lointain,<\/span><\/p>\n<p class=\"q1\"><span class=\"v23_13_5\">du bout de l\u2019horizon,<\/span><\/p>\n<p class=\"q1\"><span class=\"v23_13_5\">pour d\u00e9vaster tout le pays :<\/span><\/p>\n<p class=\"q1\"><span class=\"v23_13_5\">c\u2019est le Seigneur et ceux dont il se sert<\/span><\/p>\n<p class=\"q1\"><span class=\"v23_13_5\">pour manifester sa fureur.<\/span><\/p>\n<p class=\"b\"><\/p>\n<p class=\"q1\"><span class=\"v23_13_6\"><sup id=\"Isa.13.6\" class=\"v23_13_6\">6<\/sup>Entonnez une complainte,<\/span><\/p>\n<p class=\"q1\"><span class=\"v23_13_6\">car le jour du Seigneur n\u2019est pas loin,<\/span><\/p>\n<p class=\"q1\"><span class=\"v23_13_6\">il vient comme un d\u00e9sastre,<\/span><\/p>\n<p class=\"q1\"><span class=\"v23_13_6\">envoy\u00e9 par le Dieu tr\u00e8s-grand.<\/span><\/p>\n<p class=\"q1\"><span class=\"v23_13_7\"><sup id=\"Isa.13.7\" class=\"v23_13_7\">7<\/sup>C\u2019est pourquoi tous les bras sont inertes,<\/span><\/p>\n<p class=\"q1\"><span class=\"v23_13_7\">les hommes perdent courage.<\/span><\/p>\n<p class=\"q1\"><span class=\"v23_13_8\"><sup id=\"Isa.13.8\" class=\"v23_13_8\">8<\/sup>Les voil\u00e0 d\u00e9moralis\u00e9s,<\/span><\/p>\n<p class=\"q1\"><span class=\"v23_13_8\">saisis de douleurs et de crampes,<\/span><\/p>\n<p class=\"q1\"><span class=\"v23_13_8\">se tordant de souffrance<\/span><\/p>\n<p class=\"q1\"><span class=\"v23_13_8\">comme une femme au moment d\u2019accoucher.<\/span><\/p>\n<p class=\"q1\"><span class=\"v23_13_8\">Ils se tournent stup\u00e9faits l\u2019un vers l\u2019autre,<\/span><\/p>\n<p class=\"q1\"><span class=\"v23_13_8\">leur visage est br\u00fblant d\u2019\u00e9motion.<\/span><\/p>\n<p class=\"b\"><\/p>\n<p class=\"q1\"><span class=\"v23_13_9\"><sup id=\"Isa.13.9\" class=\"v23_13_9\">9<\/sup>Voici venir le jour du Seigneur,<\/span><\/p>\n<p class=\"q1\"><span class=\"v23_13_9\">jour de col\u00e8re impitoyable<\/span><\/p>\n<p class=\"q1\"><span class=\"v23_13_9\">et d\u2019ardente indignation.<\/span><\/p>\n<p class=\"q1\"><span class=\"v23_13_9\">Il va r\u00e9duire le pays<\/span><\/p>\n<p class=\"q1\"><span class=\"v23_13_9\">en un d\u00e9sert sinistre,<\/span><\/p>\n<p class=\"q1\"><span class=\"v23_13_9\">et en exterminer les coupables.<\/span><\/p>\n<p class=\"q1\"><span class=\"v23_13_10\"><sup id=\"Isa.13.10\" class=\"v23_13_10\">10<\/sup>Les \u00e9toiles dans le ciel<\/span><\/p>\n<p class=\"q1\"><span class=\"v23_13_10\">et les constellations<\/span><\/p>\n<p class=\"q1\"><span class=\"v23_13_10\">cessent de scintiller.<\/span><\/p>\n<p class=\"q1\"><span class=\"v23_13_10\">Le soleil, d\u00e8s qu\u2019il se l\u00e8ve, est obscurci,<\/span><\/p>\n<p class=\"q1\"><span class=\"v23_13_10\">et la lune ne r\u00e9pand plus sa clart\u00e9.<\/span><\/p>\n<p class=\"q1\"><span class=\"v23_13_11\"><sup id=\"Isa.13.11\" class=\"v23_13_11\">11<\/sup>\u00ab J\u2019interviendrai, dit le Seigneur,<\/span><\/p>\n<p class=\"q1\"><span class=\"v23_13_11\">contre la m\u00e9chancet\u00e9 du monde,<\/span><\/p>\n<p class=\"q1\"><span class=\"v23_13_11\">contre les crimes des m\u00e9chants.<\/span><\/p>\n<p class=\"q1\"><span class=\"v23_13_11\">Je mettrai fin \u00e0 l\u2019orgueil des insolents,<\/span><\/p>\n<p class=\"q1\"><span class=\"v23_13_11\">et je rabattrai la fiert\u00e9 des tyrans.<\/span><\/p>\n<p class=\"q1\"><span class=\"v23_13_12\"><sup id=\"Isa.13.12\" class=\"v23_13_12\">12<\/sup>Je rendrai les humains<\/span><\/p>\n<p class=\"q1\"><span class=\"v23_13_12\">plus rares que l\u2019or fin,<\/span><\/p>\n<p class=\"q1\"><span class=\"v23_13_12\">plus rares que l\u2019or d\u2019Ofir. \u00bb<\/span><\/p>\n<p class=\"b\"><\/p>\n<p class=\"q1\"><span class=\"v23_13_13\"><sup id=\"Isa.13.13\" class=\"v23_13_13\">13<\/sup>Le ciel sera \u00e9branl\u00e9,<\/span><\/p>\n<p class=\"q1\"><span class=\"v23_13_13\">la terre sursautera sur place,<\/span><\/p>\n<p class=\"q1\"><span class=\"v23_13_13\">sous l\u2019effet de la col\u00e8re<\/span><\/p>\n<p class=\"q1\"><span class=\"v23_13_13\">du Seigneur de l\u2019univers,<\/span><\/p>\n<p class=\"q1\"><span class=\"v23_13_13\">le jour o\u00f9 \u00e9clatera<\/span><\/p>\n<p class=\"q1\"><span class=\"v23_13_13\">son ardente indignation.<\/span><\/p>\n<p class=\"q1\"><span class=\"v23_13_14\"><sup id=\"Isa.13.14\" class=\"v23_13_14\">14<\/sup>Alors on croira voir<\/span><\/p>\n<p class=\"q1\"><span class=\"v23_13_14\">des gazelles effarouch\u00e9es<\/span><\/p>\n<p class=\"q1\"><span class=\"v23_13_14\">ou des moutons sans surveillance :<\/span><\/p>\n<p class=\"q1\"><span class=\"v23_13_14\">chacun rejoindra son peuple,<\/span><\/p>\n<p class=\"q1\"><span class=\"v23_13_14\">chacun regagnera son pays.<\/span><\/p>\n<p class=\"q1\"><span class=\"v23_13_15\"><sup id=\"Isa.13.15\" class=\"v23_13_15\">15<\/sup>Le premier qu\u2019on trouvera<\/span><\/p>\n<p class=\"q1\"><span class=\"v23_13_15\">sera cribl\u00e9 de fl\u00e8ches,<\/span><\/p>\n<p class=\"q1\"><span class=\"v23_13_15\">et quiconque sera pris<\/span><\/p>\n<p class=\"q1\"><span class=\"v23_13_15\">tombera sous les coups d\u2019\u00e9p\u00e9e.<\/span><\/p>\n<p class=\"q1\"><span class=\"v23_13_16\"><sup id=\"Isa.13.16\" class=\"v23_13_16\">16<\/sup>Ils verront leurs enfants \u00e9cras\u00e9s,<\/span><\/p>\n<p class=\"q1\"><span class=\"v23_13_16\">leurs maisons pill\u00e9es, leurs femmes viol\u00e9es.<\/span><\/p>\n<p class=\"b\"><\/p>\n<p class=\"q1\"><span class=\"v23_13_17\"><sup id=\"Isa.13.17\" class=\"v23_13_17\">17<\/sup>\u00ab Je vais leur susciter<\/span><\/p>\n<p class=\"q1\"><span class=\"v23_13_17\">des ennemis, les M\u00e8des,<\/span><\/p>\n<p class=\"q1\"><span class=\"v23_13_17\">ces gens indiff\u00e9rents \u00e0 l\u2019argent<\/span><\/p>\n<p class=\"q1\"><span class=\"v23_13_17\">et qui font fi de l\u2019or, dit le Seigneur.<\/span><\/p>\n<p class=\"q1\"><span class=\"v23_13_18\"><sup id=\"Isa.13.18\" class=\"v23_13_18\">18<\/sup>Leurs fl\u00e8ches abattent les jeunes gens ;<\/span><\/p>\n<p class=\"q1\"><span class=\"v23_13_18\">ils n\u2019\u00e9pargnent pas les nouveau-n\u00e9s,<\/span><\/p>\n<p class=\"q1\"><span class=\"v23_13_18\">ils sont sans piti\u00e9 pour les enfants. \u00bb<\/span><\/p>\n<p class=\"b\"><\/p>\n<p class=\"q1\"><span class=\"v23_13_19\"><sup id=\"Isa.13.19\" class=\"v23_13_19\">19<\/sup>Babylone, joyau de l\u2019empire,<\/span><\/p>\n<p class=\"q1\"><span class=\"v23_13_19\">fi\u00e8re parure des Babyloniens,<\/span><\/p>\n<p class=\"q1\"><span class=\"v23_13_19\">subira le bouleversement<\/span><\/p>\n<p class=\"q1\"><span class=\"v23_13_19\">que Dieu a inflig\u00e9 jadis<\/span><\/p>\n<p class=\"q1\"><span class=\"v23_13_19\">\u00e0 Sodome et \u00e0 Gomorrhe.<\/span><\/p>\n<p class=\"q1\"><span class=\"v23_13_20\"><sup id=\"Isa.13.20\" class=\"v23_13_20\">20<\/sup>Pour toujours Babylone<\/span><\/p>\n<p class=\"q1\"><span class=\"v23_13_20\">restera d\u00e9peupl\u00e9e,<\/span><\/p>\n<p class=\"q1\"><span class=\"v23_13_20\">de si\u00e8cle en si\u00e8cle inhabit\u00e9e.<\/span><\/p>\n<p class=\"q1\"><span class=\"v23_13_20\">M\u00eame les nomades<\/span><\/p>\n<p class=\"q1\"><span class=\"v23_13_20\">n\u2019y dresseront pas leur tente,<\/span><\/p>\n<p class=\"q1\"><span class=\"v23_13_20\">m\u00eame les bergers<\/span><\/p>\n<p class=\"q1\"><span class=\"v23_13_20\">n\u2019y feront pas de halte.<\/span><\/p>\n<p class=\"q1\"><span class=\"v23_13_21\"><sup id=\"Isa.13.21\" class=\"v23_13_21\">21<\/sup>Mais les chats sauvages<\/span><\/p>\n<p class=\"q1\"><span class=\"v23_13_21\">y auront leur g\u00eete,<\/span><\/p>\n<p class=\"q1\"><span class=\"v23_13_21\">et les hiboux<\/span><\/p>\n<p class=\"q1\"><span class=\"v23_13_21\">hanteront ses maisons.<\/span><\/p>\n<p class=\"q1\"><span class=\"v23_13_21\">Les autruches y feront leur demeure<\/span><\/p>\n<p class=\"q1\"><span class=\"v23_13_21\">et les boucs y danseront.<\/span><\/p>\n<p class=\"q1\"><span class=\"v23_13_22\"><sup id=\"Isa.13.22\" class=\"v23_13_22\">22<\/sup>Les hy\u00e8nes trouveront un abri<\/span><\/p>\n<p class=\"q1\"><span class=\"v23_13_22\">dans les ch\u00e2teaux de la ville,<\/span><\/p>\n<p class=\"q1\"><span class=\"v23_13_22\">et les chacals<\/span><\/p>\n<p class=\"q1\"><span class=\"v23_13_22\">dans ses palais d\u2019agr\u00e9ment.<\/span><\/p>\n<p class=\"q1\"><span class=\"v23_13_22\">Le moment est proche, il arrive,<\/span><\/p>\n<p class=\"q1\"><span class=\"v23_13_22\">Babylone n\u2019aura pas<\/span><\/p>\n<p class=\"q1\"><span class=\"v23_13_22\">un seul jour de sursis.<\/span><\/p>\n<p class=\"b\"><\/p>\n<\/div>\n","chapter":"13","id":"fra-FRC97:Isa.13","osis_end":"fra-FRC97:Isa.13.22","order":"23013","link":"fra-FRC97\/Isa\/13","display":"\u00c9sa\u00efe 13","book":{"version_id":"232","name":"\u00c9sa\u00efe","abbr":"Isa","ord":"23","book_group_id":"0","testament":"OT","id":"fra-FRC97:Isa","osis_end":"fra-FRC97:Isa.66.24"},"version":{"auditid":"0","display_abbreviation":"FRC97","version":"fra-FRC97","id":"fra-FRC97","name":"La Bible en fran\u00e7ais courant","short_desc":null,"description":null,"active":1,"active_api":0,"listed":1,"orderindex":"99","lang":"fra","lang_code":"ISO 639-3","copyright":"<p>Copyright &#169; 1997, Soci&#233;t&#233; biblique fran&#231;aise. Avec autorisation. Tous droits r&#233;serv&#233;s.<\/p>","contact_url":"http:\/\/www.la-bible.net\/","audio":"NONE","sections":[{"version_id":"fra-FRC97","id":"OT","name":"Old Testament"},{"version_id":"fra-FRC97","id":"NT","name":"New Testament"}]},"audio":null,"prevChapterId":"fra-FRC97:Isa.12","nextChapterId":"fra-FRC97:Isa.14","footnotes":[],"crossreferences":[]},"prevChapter":{"auditid":"0","label":"","text":"<div id=\"Isa.11\" class=\"chapter\">\n<h3 class=\"s1\">Un nouveau David<\/h3>\n<p class=\"q1\"><span class=\"v23_11_1\"><sup id=\"Isa.11.1\" class=\"v23_11_1\">1<\/sup>Un rameau sort du vieux tronc de Jess\u00e9,<\/span><\/p>\n<p class=\"q1\"><span class=\"v23_11_1\">un rejeton pousse de ses racines.<\/span><\/p>\n<p class=\"q1\"><span class=\"v23_11_2\"><sup id=\"Isa.11.2\" class=\"v23_11_2\">2<\/sup>L\u2019Esprit du Seigneur est sans cesse avec lui,<\/span><\/p>\n<p class=\"q1\"><span class=\"v23_11_2\">l\u2019Esprit qui donne sagesse et discernement,<\/span><\/p>\n<p class=\"q1\"><span class=\"v23_11_2\">aptitude \u00e0 d\u00e9cider et vaillance,<\/span><\/p>\n<p class=\"q1\"><span class=\"v23_11_2\">l\u2019Esprit qui fait conna\u00eetre le Seigneur<\/span><\/p>\n<p class=\"q1\"><span class=\"v23_11_2\">et enseigne \u00e0 l\u2019honorer.<\/span><\/p>\n<p class=\"q1\"><span class=\"v23_11_3\"><sup id=\"Isa.11.3\" class=\"v23_11_3\">3<\/sup>Honorer le Seigneur sera tout son plaisir.<\/span><\/p>\n<p class=\"q1\"><span class=\"v23_11_3\">Il ne jugera pas selon les apparences,<\/span><\/p>\n<p class=\"q1\"><span class=\"v23_11_3\">il ne d\u00e9cidera rien d\u2019apr\u00e8s des racontars.<\/span><\/p>\n<p class=\"q1\"><span class=\"v23_11_4\"><sup id=\"Isa.11.4\" class=\"v23_11_4\">4<\/sup>Mais il rendra justice aux d\u00e9favoris\u00e9s,<\/span><\/p>\n<p class=\"q1\"><span class=\"v23_11_4\">il sera juste pour les pauvres du pays.<\/span><\/p>\n<p class=\"q1\"><span class=\"v23_11_4\">Sa parole, comme un b\u00e2ton, frappera le pays,<\/span><\/p>\n<p class=\"q1\"><span class=\"v23_11_4\">sa sentence fera mourir le m\u00e9chant.<\/span><\/p>\n<p class=\"q1\"><span class=\"v23_11_5\"><sup id=\"Isa.11.5\" class=\"v23_11_5\">5<\/sup>La justice et la fid\u00e9lit\u00e9<\/span><\/p>\n<p class=\"q1\"><span class=\"v23_11_5\">seront pour lui comme la ceinture<\/span><\/p>\n<p class=\"q1\"><span class=\"v23_11_5\">qu\u2019on porte toujours autour des reins.<\/span><\/p>\n<p class=\"q1\"><span class=\"v23_11_6\"><sup id=\"Isa.11.6\" class=\"v23_11_6\">6<\/sup>Alors le loup s\u00e9journera avec l\u2019agneau,<\/span><\/p>\n<p class=\"q1\"><span class=\"v23_11_6\">la panth\u00e8re aura son g\u00eete avec le chevreau.<\/span><\/p>\n<p class=\"q1\"><span class=\"v23_11_6\">Le veau et le lionceau se nourriront ensemble,<\/span><\/p>\n<p class=\"q1\"><span class=\"v23_11_6\">et un petit gar\u00e7on les conduira.<\/span><\/p>\n<p class=\"q1\"><span class=\"v23_11_7\"><sup id=\"Isa.11.7\" class=\"v23_11_7\">7<\/sup>La vache et l\u2019ourse se lieront d\u2019amiti\u00e9,<\/span><\/p>\n<p class=\"q1\"><span class=\"v23_11_7\">leurs petits seront couch\u00e9s c\u00f4te \u00e0 c\u00f4te.<\/span><\/p>\n<p class=\"q1\"><span class=\"v23_11_7\">Le lion comme le b\u0153uf mangera du fourrage.<\/span><\/p>\n<p class=\"q1\"><span class=\"v23_11_8\"><sup id=\"Isa.11.8\" class=\"v23_11_8\">8<\/sup>Le nourrisson jouera sur le nid du serpent,<\/span><\/p>\n<p class=\"q1\"><span class=\"v23_11_8\">et le petit gar\u00e7on pourra mettre la main<\/span><\/p>\n<p class=\"q1\"><span class=\"v23_11_8\">dans la cachette de la vip\u00e8re.<\/span><\/p>\n<p class=\"q1\"><span class=\"v23_11_9\"><sup id=\"Isa.11.9\" class=\"v23_11_9\">9<\/sup>On ne commettra ni mal ni dommage<\/span><\/p>\n<p class=\"q1\"><span class=\"v23_11_9\">sur toute la montagne consacr\u00e9e au Seigneur,<\/span><\/p>\n<p class=\"q1\"><span class=\"v23_11_9\">car la connaissance du Seigneur<\/span><\/p>\n<p class=\"q1\"><span class=\"v23_11_9\">remplira le pays aussi parfaitement<\/span><\/p>\n<p class=\"q1\"><span class=\"v23_11_9\">que les eaux recouvrent le fond des mers.<\/span><\/p>\n<p class=\"q1\"><span class=\"v23_11_10\"><sup id=\"Isa.11.10\" class=\"v23_11_10\">10<\/sup>Ce jour-l\u00e0, le descendant de Jess\u00e9<\/span><\/p>\n<p class=\"q1\"><span class=\"v23_11_10\">sera comme un signal dress\u00e9<\/span><\/p>\n<p class=\"q1\"><span class=\"v23_11_10\">pour les peuples du monde.<\/span><\/p>\n<p class=\"q1\"><span class=\"v23_11_10\">Les nations viendront le consulter.<\/span><\/p>\n<p class=\"q1\"><span class=\"v23_11_10\">Et du lieu o\u00f9 il s\u2019\u00e9tablira<\/span><\/p>\n<p class=\"q1\"><span class=\"v23_11_10\">rayonnera la glorieuse pr\u00e9sence de Dieu.<\/span><\/p>\n<h3 class=\"s1\">Le retour des exil\u00e9s<\/h3>\n<p class=\"q1\"><span class=\"v23_11_11\"><sup id=\"Isa.11.11\" class=\"v23_11_11\">11<\/sup>Ce jour-l\u00e0, une fois encore,<\/span><\/p>\n<p class=\"q1\"><span class=\"v23_11_11\">le Seigneur agira<\/span><\/p>\n<p class=\"q1\"><span class=\"v23_11_11\">pour racheter le reste de son peuple,<\/span><\/p>\n<p class=\"q1\"><span class=\"v23_11_11\">ceux qui auront surv\u00e9cu<\/span><\/p>\n<p class=\"q1\"><span class=\"v23_11_11\">en Assyrie, en Basse-\u00c9gypte,<\/span><\/p>\n<p class=\"q1\"><span class=\"v23_11_11\">en Haute-\u00c9gypte, en \u00c9thiopie,<\/span><\/p>\n<p class=\"q1\"><span class=\"v23_11_11\">en \u00c9lam, en Babylonie,<\/span><\/p>\n<p class=\"q1\"><span class=\"v23_11_11\">\u00e0 Hamath-en-Syrie<\/span><\/p>\n<p class=\"q1\"><span class=\"v23_11_11\">et dans les r\u00e9gions maritimes.<\/span><\/p>\n<p class=\"q1\"><span class=\"v23_11_12\"><sup id=\"Isa.11.12\" class=\"v23_11_12\">12<\/sup>Il dressera un signal<\/span><\/p>\n<p class=\"q1\"><span class=\"v23_11_12\">pour avertir ces nations<\/span><\/p>\n<p class=\"q1\"><span class=\"v23_11_12\">qu\u2019il va rassembler les exil\u00e9s d\u2019Isra\u00ebl<\/span><\/p>\n<p class=\"q1\"><span class=\"v23_11_12\">et regrouper les Jud\u00e9ens<\/span><\/p>\n<p class=\"q1\"><span class=\"v23_11_12\">dispers\u00e9s aux quatre coins du monde.<\/span><\/p>\n<p class=\"q1\"><span class=\"v23_11_13\"><sup id=\"Isa.11.13\" class=\"v23_11_13\">13<\/sup>Alors cessera<\/span><\/p>\n<p class=\"q1\"><span class=\"v23_11_13\">la jalousie d\u2019\u00c9fra\u00efm envers Juda,<\/span><\/p>\n<p class=\"q1\"><span class=\"v23_11_13\">les agresseurs de Juda seront \u00e9limin\u00e9s.<\/span><\/p>\n<p class=\"q1\"><span class=\"v23_11_13\">\u00c9fra\u00efm ne sera plus jaloux de Juda<\/span><\/p>\n<p class=\"q1\"><span class=\"v23_11_13\">Juda ne sera plus agressif envers \u00c9fra\u00efm.<\/span><\/p>\n<p class=\"q1\"><span class=\"v23_11_14\"><sup id=\"Isa.11.14\" class=\"v23_11_14\">14<\/sup>Vers l\u2019ouest, ils fonceront ensemble<\/span><\/p>\n<p class=\"q1\"><span class=\"v23_11_14\">sur les collines de Philistie,<\/span><\/p>\n<p class=\"q1\"><span class=\"v23_11_14\">vers l\u2019est, ils iront piller<\/span><\/p>\n<p class=\"q1\"><span class=\"v23_11_14\">les tribus du d\u00e9sert :<\/span><\/p>\n<p class=\"q1\"><span class=\"v23_11_14\">ils \u00e9tendront leur pouvoir<\/span><\/p>\n<p class=\"q1\"><span class=\"v23_11_14\">sur \u00c9dom et sur Moab,<\/span><\/p>\n<p class=\"q1\"><span class=\"v23_11_14\">et les Ammonites leur seront soumis.<\/span><\/p>\n<p class=\"q1\"><span class=\"v23_11_15\"><sup id=\"Isa.11.15\" class=\"v23_11_15\">15<\/sup>Le Seigneur ass\u00e9chera<\/span><\/p>\n<p class=\"q1\"><span class=\"v23_11_15\">le golfe d\u2019\u00c9gypte.<\/span><\/p>\n<p class=\"q1\"><span class=\"v23_11_15\">Il menacera l\u2019Euphrate<\/span><\/p>\n<p class=\"q1\"><span class=\"v23_11_15\">d\u2019un geste de la main ;<\/span><\/p>\n<p class=\"q1\"><span class=\"v23_11_15\">par la puissance de son souffle,<\/span><\/p>\n<p class=\"q1\"><span class=\"v23_11_15\">il le r\u00e9duira en sept ruisseaux<\/span><\/p>\n<p class=\"q1\"><span class=\"v23_11_15\">qu\u2019on pourra passer \u00e0 pied sec.<\/span><\/p>\n<p class=\"q1\"><span class=\"v23_11_16\"><sup id=\"Isa.11.16\" class=\"v23_11_16\">16<\/sup>Il y aura une route<\/span><\/p>\n<p class=\"q1\"><span class=\"v23_11_16\">pour le reste de son peuple,<\/span><\/p>\n<p class=\"q1\"><span class=\"v23_11_16\">qui aura surv\u00e9cu en Assyrie,<\/span><\/p>\n<p class=\"q1\"><span class=\"v23_11_16\">comme il y en eut une jadis<\/span><\/p>\n<p class=\"q1\"><span class=\"v23_11_16\">pour Isra\u00ebl, quand il quitta l\u2019\u00c9gypte.<\/span><\/p>\n<p class=\"b\"><\/p>\n<\/div>\n","chapter":"11","id":"fra-FRC97:Isa.11","osis_end":"fra-FRC97:Isa.11.16","order":"23011","link":"fra-FRC97\/Isa\/11","display":"\u00c9sa\u00efe 11","book":{"version_id":"232","name":"\u00c9sa\u00efe","abbr":"Isa","ord":"23","book_group_id":"0","testament":"OT","id":"fra-FRC97:Isa","osis_end":"fra-FRC97:Isa.66.24"},"version":{"auditid":"0","display_abbreviation":"FRC97","version":"fra-FRC97","id":"fra-FRC97","name":"La Bible en fran\u00e7ais courant","short_desc":null,"description":null,"active":1,"active_api":0,"listed":1,"orderindex":"99","lang":"fra","lang_code":"ISO 639-3","copyright":"<p>Copyright &#169; 1997, Soci&#233;t&#233; biblique fran&#231;aise. Avec autorisation. Tous droits r&#233;serv&#233;s.<\/p>","contact_url":"http:\/\/www.la-bible.net\/","audio":"NONE","sections":[{"version_id":"fra-FRC97","id":"OT","name":"Old Testament"},{"version_id":"fra-FRC97","id":"NT","name":"New Testament"}]},"audio":null,"prevChapterId":"fra-FRC97:Isa.10","nextChapterId":"fra-FRC97:Isa.12","footnotes":[],"crossreferences":[]},"footnotes":[],"crossreferences":[]}