{"auditid":"0","label":"","text":"<div id=\"Isa.61\" class=\"chapter\">\n<h3 class=\"s1\">El ungido, mensajero de liberaci\u00f3n y de consuelo<\/h3>\n<p class=\"q\"><span class=\"v23_61_1\"><sup id=\"Isa.61.1\" class=\"v23_61_1\">1<\/sup>El esp\u00edritu del Se\u00f1or Dios me acompa\u00f1a,<\/span><\/p>\n<p class=\"q\"><span class=\"v23_61_1\">pues el propio Se\u00f1or me ha ungido,<\/span><\/p>\n<p class=\"q\"><span class=\"v23_61_1\">me ha enviado a dar la buena noticia a los pobres,<\/span><\/p>\n<p class=\"q\"><span class=\"v23_61_1\">a vendar los corazones destrozados,<\/span><\/p>\n<p class=\"q\"><span class=\"v23_61_1\">a proclamar la libertad a los cautivos,<\/span><\/p>\n<p class=\"q\"><span class=\"v23_61_1\">a gritar la liberaci\u00f3n a los prisioneros,<\/span><\/p>\n<p class=\"q\"><span class=\"v23_61_2\"><sup id=\"Isa.61.2\" class=\"v23_61_2\">2<\/sup>a proclamar un a\u00f1o de gracia del Se\u00f1or<\/span><\/p>\n<p class=\"q\"><span class=\"v23_61_2\">y un d\u00eda de venganza de parte de nuestro Dios;<\/span><\/p>\n<p class=\"q\"><span class=\"v23_61_2\">a dar consuelo a los que est\u00e1n de luto,<\/span><\/p>\n<p class=\"q\"><span class=\"v23_61_3\"><sup id=\"Isa.61.3\" class=\"v23_61_3\">3<\/sup>a cubrirlos de honor en lugar de polvo,<\/span><\/p>\n<p class=\"q\"><span class=\"v23_61_3\">de perfume de fiesta en lugar de penas,<\/span><\/p>\n<p class=\"q\"><span class=\"v23_61_3\">de traje festivo en lugar de abatimiento.<\/span><\/p>\n<p class=\"q\"><span class=\"v23_61_3\">Los llamar\u00e1n \u201crobles fruto de la justicia\u201d,<\/span><\/p>\n<p class=\"q\"><span class=\"v23_61_3\">plant\u00edo para gloria del Se\u00f1or.<\/span><\/p>\n<p class=\"q\"><span class=\"v23_61_4\"><sup id=\"Isa.61.4\" class=\"v23_61_4\">4<\/sup>Reconstruir\u00e1n las ruinas antiguas,<\/span><\/p>\n<p class=\"q\"><span class=\"v23_61_4\">reedificar\u00e1n los escombros de anta\u00f1o,<\/span><\/p>\n<p class=\"q\"><span class=\"v23_61_4\">renovar\u00e1n las ciudades devastadas,<\/span><\/p>\n<p class=\"q\"><span class=\"v23_61_4\">los escombros abandonados por generaciones.<\/span><\/p>\n<p class=\"q\"><span class=\"v23_61_5\"><sup id=\"Isa.61.5\" class=\"v23_61_5\">5<\/sup>Se ver\u00e1n extra\u00f1os pastoreando su ganado,<\/span><\/p>\n<p class=\"q\"><span class=\"v23_61_5\">extranjeros trabajar\u00e1n sus campos y vi\u00f1as,<\/span><\/p>\n<p class=\"q\"><span class=\"v23_61_6\"><sup id=\"Isa.61.6\" class=\"v23_61_6\">6<\/sup>y a ustedes los proclamar\u00e1n sacerdotes del Se\u00f1or,<\/span><\/p>\n<p class=\"q\"><span class=\"v23_61_6\">les llamar\u00e1n servidores de nuestro Dios.<\/span><\/p>\n<p class=\"q\"><span class=\"v23_61_6\">Los har\u00e1n con la riqueza de las naciones,<\/span><\/p>\n<p class=\"q\"><span class=\"v23_61_6\">sus posesiones pasar\u00e1n a\u00a0las manos de ustedes.<\/span><\/p>\n<p class=\"q\"><span class=\"v23_61_7\"><sup id=\"Isa.61.7\" class=\"v23_61_7\">7<\/sup>A cambio de su verg\u00fcenza doblada,<\/span><\/p>\n<p class=\"q\"><span class=\"v23_61_7\">hecha de ultrajes y de oprobio,<\/span><\/p>\n<p class=\"q\"><span class=\"v23_61_7\">poseer\u00e1n doble recompensa en su tierra,<\/span><\/p>\n<p class=\"q\"><span class=\"v23_61_7\">ser\u00e1n felices para siempre.<\/span><\/p>\n<p class=\"q\"><span class=\"v23_61_8\"><sup id=\"Isa.61.8\" class=\"v23_61_8\">8<\/sup>Yo, el Se\u00f1or, amo la justicia,<\/span><\/p>\n<p class=\"q\"><span class=\"v23_61_8\">detesto el pillaje y el crimen;<\/span><\/p>\n<p class=\"q\"><span class=\"v23_61_8\">les dar\u00e9 cumplida recompensa,<\/span><\/p>\n<p class=\"q\"><span class=\"v23_61_8\">har\u00e9 con ellos una alianza eterna.<\/span><\/p>\n<p class=\"q\"><span class=\"v23_61_9\"><sup id=\"Isa.61.9\" class=\"v23_61_9\">9<\/sup>Sus hijos ser\u00e1n famosos entre las naciones,<\/span><\/p>\n<p class=\"q\"><span class=\"v23_61_9\">sus v\u00e1stagos entre todos los pueblos.<\/span><\/p>\n<p class=\"q\"><span class=\"v23_61_9\">Todos los que los vean reconocer\u00e1n<\/span><\/p>\n<p class=\"q\"><span class=\"v23_61_9\">que son la estirpe bendita del Se\u00f1or.<\/span><\/p>\n<h3 class=\"s1\">Himno de victoria<\/h3>\n<p class=\"q\"><span class=\"v23_61_10\"><sup id=\"Isa.61.10\" class=\"v23_61_10\">10<\/sup>Reboso de dicha en el Se\u00f1or,<\/span><\/p>\n<p class=\"q\"><span class=\"v23_61_10\">me alegro animoso en mi Dios,<\/span><\/p>\n<p class=\"q\"><span class=\"v23_61_10\">que me ha puesto un vestido de fiesta,<\/span><\/p>\n<p class=\"q\"><span class=\"v23_61_10\">me ha envuelto en un manto de victoria,<\/span><\/p>\n<p class=\"q\"><span class=\"v23_61_10\">como un novio que se pone la corona,<\/span><\/p>\n<p class=\"q\"><span class=\"v23_61_10\">como novia que se viste sus atuendos.<\/span><\/p>\n<p class=\"q\"><span class=\"v23_61_11\"><sup id=\"Isa.61.11\" class=\"v23_61_11\">11<\/sup>Igual que la tierra produce sus renuevos,<\/span><\/p>\n<p class=\"q\"><span class=\"v23_61_11\">lo mismo que germinan brotes en un jard\u00edn,<\/span><\/p>\n<p class=\"q\"><span class=\"v23_61_11\">as\u00ed hace germinar el Se\u00f1or Dios la liberaci\u00f3n<\/span><\/p>\n<p class=\"q\"><span class=\"v23_61_11\">y el canto de triunfo ante todos los pueblos.<\/span><\/p>\n<\/div>\n","chapter":"61","id":"spa-BHTI:Isa.61","osis_end":"spa-BHTI:Isa.61.11","order":"23061","link":"spa-BHTI\/Isa\/61","display":"ISA\u00cdAS 61","book":{"version_id":"173","name":"ISA\u00cdAS","abbr":"Isa","ord":"23","book_group_id":"0","testament":"OT","id":"spa-BHTI:Isa","osis_end":"spa-BHTI:Isa.66.24"},"version":{"auditid":"0","display_abbreviation":"BHTI","version":"spa-BHTI","id":"spa-BHTI","name":"La Biblia Hispanoamericana (Traducci\u00f3n Interconfesional, versi\u00f3n hispanoamericana)","short_desc":null,"description":null,"active":1,"active_api":0,"listed":1,"orderindex":"99","lang":"spa","lang_code":"ISO 639-3","copyright":"<p>La Biblia Hispanoamericana (BHTI) Traducci&#243;n Interconfesional versi&#243;n hispanoamericana Copyright &#169; Sociedad B&#237;blica de Espa&#241;a, 2011 Utilizada con permiso<\/p>","contact_url":"http:\/\/sociedadbiblica.org","audio":"NONE","sections":[{"version_id":"spa-BHTI","id":"OT","name":"Old Testament"},{"version_id":"spa-BHTI","id":"NT","name":"New Testament"}]},"audio":null,"prevChapterId":"spa-BHTI:Isa.60","nextChapterId":"spa-BHTI:Isa.62","nextChapter":{"auditid":"0","label":"","text":"<div id=\"Isa.62\" class=\"chapter\">\n<h3 class=\"s1\">El Se\u00f1or se desposa con Jerusal\u00e9n<\/h3>\n<p class=\"q\"><span class=\"v23_62_1\"><sup id=\"Isa.62.1\" class=\"v23_62_1\">1<\/sup>Por amor de Si\u00f3n no callar\u00e9,<\/span><\/p>\n<p class=\"q\"><span class=\"v23_62_1\">no descansar\u00e9 por Jerusal\u00e9n,<\/span><\/p>\n<p class=\"q\"><span class=\"v23_62_1\">hasta que irradie su justicia como luz<\/span><\/p>\n<p class=\"q\"><span class=\"v23_62_1\">y arda como antorcha su salvaci\u00f3n.<\/span><\/p>\n<p class=\"q\"><span class=\"v23_62_2\"><sup id=\"Isa.62.2\" class=\"v23_62_2\">2<\/sup>Ver\u00e1n las naciones tu prosperidad,<\/span><\/p>\n<p class=\"q\"><span class=\"v23_62_2\">los reyes contemplar\u00e1n tu grandeza,<\/span><\/p>\n<p class=\"q\"><span class=\"v23_62_2\">y te pondr\u00e1n un nombre nuevo,<\/span><\/p>\n<p class=\"q\"><span class=\"v23_62_2\">designado por la boca del Se\u00f1or.<\/span><\/p>\n<p class=\"q\"><span class=\"v23_62_3\"><sup id=\"Isa.62.3\" class=\"v23_62_3\">3<\/sup>Ser\u00e1s corona de honor en mano del Se\u00f1or<\/span><\/p>\n<p class=\"q\"><span class=\"v23_62_3\">y diadema real en la palma de tu Dios.<\/span><\/p>\n<p class=\"q\"><span class=\"v23_62_4\"><sup id=\"Isa.62.4\" class=\"v23_62_4\">4<\/sup>Ya no te llamar\u00e1n \u201cAbandonada\u201d,<\/span><\/p>\n<p class=\"q\"><span class=\"v23_62_4\">ni dir\u00e1n a tu tierra \u201cDesolada\u201d,<\/span><\/p>\n<p class=\"q\"><span class=\"v23_62_4\">pues te llamar\u00e1n \u201cQuerida m\u00eda\u201d,<\/span><\/p>\n<p class=\"q\"><span class=\"v23_62_4\">dir\u00e1n a tu tierra \u201cDesposada\u201d;<\/span><\/p>\n<p class=\"q\"><span class=\"v23_62_4\">pues el Se\u00f1or te quiere a ti<\/span><\/p>\n<p class=\"q\"><span class=\"v23_62_4\">y tu tierra tendr\u00e1 ya marido.<\/span><\/p>\n<p class=\"q\"><span class=\"v23_62_5\"><sup id=\"Isa.62.5\" class=\"v23_62_5\">5<\/sup>Como un joven se casa con su novia,<\/span><\/p>\n<p class=\"q\"><span class=\"v23_62_5\">as\u00ed te desposa quien te construy\u00f3;<\/span><\/p>\n<p class=\"q\"><span class=\"v23_62_5\">la alegr\u00eda del novio por su novia<\/span><\/p>\n<p class=\"q\"><span class=\"v23_62_5\">es la alegr\u00eda de tu Dios por ti.<\/span><\/p>\n<p class=\"q\"><span class=\"v23_62_6\"><sup id=\"Isa.62.6\" class=\"v23_62_6\">6<\/sup>Sobre tus muros, Jerusal\u00e9n,<\/span><\/p>\n<p class=\"q\"><span class=\"v23_62_6\">he apostado centinelas;<\/span><\/p>\n<p class=\"q\"><span class=\"v23_62_6\">ni de d\u00eda ni de noche<\/span><\/p>\n<p class=\"q\"><span class=\"v23_62_6\">permanecen en silencio.<\/span><\/p>\n<p class=\"q\"><span class=\"v23_62_6\">Los que se lo recuerdan al Se\u00f1or,<\/span><\/p>\n<p class=\"q\"><span class=\"v23_62_6\">no se tomen descanso alguno;<\/span><\/p>\n<p class=\"q\"><span class=\"v23_62_7\"><sup id=\"Isa.62.7\" class=\"v23_62_7\">7<\/sup>no den descanso al Se\u00f1or<\/span><\/p>\n<p class=\"q\"><span class=\"v23_62_7\">hasta que la consolide,<\/span><\/p>\n<p class=\"q\"><span class=\"v23_62_7\">hasta que haga de Jerusal\u00e9n<\/span><\/p>\n<p class=\"q\"><span class=\"v23_62_7\">tema de alabanza en la tierra.<\/span><\/p>\n<p class=\"q\"><span class=\"v23_62_8\"><sup id=\"Isa.62.8\" class=\"v23_62_8\">8<\/sup>Lo ha jurado el Se\u00f1or solemnemente,<\/span><\/p>\n<p class=\"q\"><span class=\"v23_62_8\">levantando su brazo poderoso:<\/span><\/p>\n<p class=\"q\"><span class=\"v23_62_8\">no dar\u00e9 otra vez tu trigo<\/span><\/p>\n<p class=\"q\"><span class=\"v23_62_8\">para que lo coman tus enemigos;<\/span><\/p>\n<p class=\"q\"><span class=\"v23_62_8\">no beber\u00e1n extranjeros tu mosto,<\/span><\/p>\n<p class=\"q\"><span class=\"v23_62_8\">que tantos trabajos te cost\u00f3.<\/span><\/p>\n<p class=\"q\"><span class=\"v23_62_9\"><sup id=\"Isa.62.9\" class=\"v23_62_9\">9<\/sup>Lo comer\u00e1n los cosechadores<\/span><\/p>\n<p class=\"q\"><span class=\"v23_62_9\">y alabar\u00e1n al Se\u00f1or;<\/span><\/p>\n<p class=\"q\"><span class=\"v23_62_9\">lo beber\u00e1n los vendimiadores<\/span><\/p>\n<p class=\"q\"><span class=\"v23_62_9\">en mis santos atrios.<\/span><\/p>\n<p class=\"q\"><span class=\"v23_62_10\"><sup id=\"Isa.62.10\" class=\"v23_62_10\">10<\/sup>Pasen, pasen por las puertas,<\/span><\/p>\n<p class=\"q\"><span class=\"v23_62_10\">se\u00f1alen al pueblo el camino;<\/span><\/p>\n<p class=\"q\"><span class=\"v23_62_10\">allanen, allanen la calzada,<\/span><\/p>\n<p class=\"q\"><span class=\"v23_62_10\">d\u00e9jenla bien despedregada;<\/span><\/p>\n<p class=\"q\"><span class=\"v23_62_10\">icen una ense\u00f1a a los pueblos.<\/span><\/p>\n<p class=\"q\"><span class=\"v23_62_11\"><sup id=\"Isa.62.11\" class=\"v23_62_11\">11<\/sup>El Se\u00f1or proclama un mensaje<\/span><\/p>\n<p class=\"q\"><span class=\"v23_62_11\">hasta el conf\u00edn de la tierra:<\/span><\/p>\n<p class=\"q\"><span class=\"v23_62_11\">Digan a la ciudad de Si\u00f3n:<\/span><\/p>\n<p class=\"q\"><span class=\"v23_62_11\">\u201cya est\u00e1 aqu\u00ed tu Salvador;<\/span><\/p>\n<p class=\"q\"><span class=\"v23_62_11\">con \u00e9l llega su recompensa,<\/span><\/p>\n<p class=\"q\"><span class=\"v23_62_11\">viene precedido de su premio\u201d.<\/span><\/p>\n<p class=\"q\"><span class=\"v23_62_12\"><sup id=\"Isa.62.12\" class=\"v23_62_12\">12<\/sup>Los llamar\u00e1n \u201cPueblo del Santo\u201d,<\/span><\/p>\n<p class=\"q\"><span class=\"v23_62_12\">les dir\u00e1n \u201cRescatados del Se\u00f1or\u201d,<\/span><\/p>\n<p class=\"q\"><span class=\"v23_62_12\">y a ti te llamar\u00e1n \u201cAnhelada\u201d,<\/span><\/p>\n<p class=\"q\"><span class=\"v23_62_12\">te dir\u00e1n \u201cCiudad no abandonada\u201d.<\/span><\/p>\n<\/div>\n","chapter":"62","id":"spa-BHTI:Isa.62","osis_end":"spa-BHTI:Isa.62.12","order":"23062","link":"spa-BHTI\/Isa\/62","display":"ISA\u00cdAS 62","book":{"version_id":"173","name":"ISA\u00cdAS","abbr":"Isa","ord":"23","book_group_id":"0","testament":"OT","id":"spa-BHTI:Isa","osis_end":"spa-BHTI:Isa.66.24"},"version":{"auditid":"0","display_abbreviation":"BHTI","version":"spa-BHTI","id":"spa-BHTI","name":"La Biblia Hispanoamericana (Traducci\u00f3n Interconfesional, versi\u00f3n hispanoamericana)","short_desc":null,"description":null,"active":1,"active_api":0,"listed":1,"orderindex":"99","lang":"spa","lang_code":"ISO 639-3","copyright":"<p>La Biblia Hispanoamericana (BHTI) Traducci&#243;n Interconfesional versi&#243;n hispanoamericana Copyright &#169; Sociedad B&#237;blica de Espa&#241;a, 2011 Utilizada con permiso<\/p>","contact_url":"http:\/\/sociedadbiblica.org","audio":"NONE","sections":[{"version_id":"spa-BHTI","id":"OT","name":"Old Testament"},{"version_id":"spa-BHTI","id":"NT","name":"New Testament"}]},"audio":null,"prevChapterId":"spa-BHTI:Isa.61","nextChapterId":"spa-BHTI:Isa.63","footnotes":[],"crossreferences":[]},"prevChapter":{"auditid":"0","label":"","text":"<div id=\"Isa.60\" class=\"chapter\">\n<h3 class=\"s1\">Futuro luminoso de Jerusal\u00e9n<\/h3>\n<p class=\"q\"><span class=\"v23_60_1\"><sup id=\"Isa.60.1\" class=\"v23_60_1\">1<\/sup>\u00a1\u00c1lzate radiante, que llega tu luz,<\/span><\/p>\n<p class=\"q\"><span class=\"v23_60_1\">la gloria del Se\u00f1or clarea sobre ti!<\/span><\/p>\n<p class=\"q\"><span class=\"v23_60_2\"><sup id=\"Isa.60.2\" class=\"v23_60_2\">2<\/sup>Mira: la tiniebla cubre la tierra,<\/span><\/p>\n<p class=\"q\"><span class=\"v23_60_2\">negros nubarrones<\/span><\/p>\n<p class=\"q\"><span class=\"v23_60_2\">se ciernen sobre los pueblos,<\/span><\/p>\n<p class=\"q\"><span class=\"v23_60_2\">mas sobre ti clarea la luz del Se\u00f1or,<\/span><\/p>\n<p class=\"q\"><span class=\"v23_60_2\">su gloria se dejar\u00e1 ver sobre ti;<\/span><\/p>\n<p class=\"q\"><span class=\"v23_60_3\"><sup id=\"Isa.60.3\" class=\"v23_60_3\">3<\/sup>los pueblos caminar\u00e1n a tu luz,<\/span><\/p>\n<p class=\"q\"><span class=\"v23_60_3\">los reyes al resplandor de tu alborada.<\/span><\/p>\n<p class=\"q\"><span class=\"v23_60_4\"><sup id=\"Isa.60.4\" class=\"v23_60_4\">4<\/sup>Alza en torno tus ojos y mira,<\/span><\/p>\n<p class=\"q\"><span class=\"v23_60_4\">todos vienen y se unen a ti;<\/span><\/p>\n<p class=\"q\"><span class=\"v23_60_4\">tus hijos llegan de lejos,<\/span><\/p>\n<p class=\"q\"><span class=\"v23_60_4\">a tus hijas las traen en brazos.<\/span><\/p>\n<p class=\"q\"><span class=\"v23_60_5\"><sup id=\"Isa.60.5\" class=\"v23_60_5\">5<\/sup>Entonces lo ver\u00e1s radiante,<\/span><\/p>\n<p class=\"q\"><span class=\"v23_60_5\">tu coraz\u00f3n se ensanchar\u00e1 maravillado,<\/span><\/p>\n<p class=\"q\"><span class=\"v23_60_5\">pues volcar\u00e1n sobre ti las riquezas del mar,<\/span><\/p>\n<p class=\"q\"><span class=\"v23_60_5\">te traer\u00e1n el patrimonio de los pueblos.<\/span><\/p>\n<p class=\"q\"><span class=\"v23_60_6\"><sup id=\"Isa.60.6\" class=\"v23_60_6\">6<\/sup>Te cubrir\u00e1 una multitud de camellos,<\/span><\/p>\n<p class=\"q\"><span class=\"v23_60_6\">de dromedarios de Madi\u00e1n y de Ef\u00e1.<\/span><\/p>\n<p class=\"q\"><span class=\"v23_60_6\">Llegan todos de Sab\u00e1,<\/span><\/p>\n<p class=\"q\"><span class=\"v23_60_6\">trayendo oro e incienso,<\/span><\/p>\n<p class=\"q\"><span class=\"v23_60_6\">proclamando las gestas del Se\u00f1or.<\/span><\/p>\n<p class=\"q\"><span class=\"v23_60_7\"><sup id=\"Isa.60.7\" class=\"v23_60_7\">7<\/sup>Traer\u00e1n para ti reba\u00f1os de Quedar,<\/span><\/p>\n<p class=\"q\"><span class=\"v23_60_7\">te regalar\u00e1n carneros de Nebayot;<\/span><\/p>\n<p class=\"q\"><span class=\"v23_60_7\">aceptar\u00e9 que los inmolen sobre mi altar,<\/span><\/p>\n<p class=\"q\"><span class=\"v23_60_7\">y as\u00ed engrandecer\u00e9 mi glorioso Templo.<\/span><\/p>\n<p class=\"q\"><span class=\"v23_60_8\"><sup id=\"Isa.60.8\" class=\"v23_60_8\">8<\/sup>\u00bfQui\u00e9nes son esos que vuelan como nubes,<\/span><\/p>\n<p class=\"q\"><span class=\"v23_60_8\">que se dirigen como palomas a su palomar?<\/span><\/p>\n<p class=\"q\"><span class=\"v23_60_9\"><sup id=\"Isa.60.9\" class=\"v23_60_9\">9<\/sup>Nav\u00edos de las islas acuden a m\u00ed,<\/span><\/p>\n<p class=\"q\"><span class=\"v23_60_9\">en primer lugar las naves de Tarsis,<\/span><\/p>\n<p class=\"q\"><span class=\"v23_60_9\">para traer a tus hijos de lejos,<\/span><\/p>\n<p class=\"q\"><span class=\"v23_60_9\">cargados con su plata y con su oro,<\/span><\/p>\n<p class=\"q\"><span class=\"v23_60_9\">para glorificar al Se\u00f1or, tu Dios,<\/span><\/p>\n<p class=\"q\"><span class=\"v23_60_9\">al Santo de Israel que te honra.<\/span><\/p>\n<p class=\"q\"><span class=\"v23_60_10\"><sup id=\"Isa.60.10\" class=\"v23_60_10\">10<\/sup>Extranjeros levantar\u00e1n tus muros,<\/span><\/p>\n<p class=\"q\"><span class=\"v23_60_10\">sus reyes estar\u00e1n a tu servicio;<\/span><\/p>\n<p class=\"q\"><span class=\"v23_60_10\">cierto que te her\u00ed en mi c\u00f3lera,<\/span><\/p>\n<p class=\"q\"><span class=\"v23_60_10\">pero ahora te quiero complacido.<\/span><\/p>\n<p class=\"q\"><span class=\"v23_60_11\"><sup id=\"Isa.60.11\" class=\"v23_60_11\">11<\/sup>Tus puertas estar\u00e1n siempre abiertas,<\/span><\/p>\n<p class=\"q\"><span class=\"v23_60_11\">no se cerrar\u00e1n ni de noche ni de d\u00eda,<\/span><\/p>\n<p class=\"q\"><span class=\"v23_60_11\">para traerte las riquezas de los pueblos,<\/span><\/p>\n<p class=\"q\"><span class=\"v23_60_11\">que vendr\u00e1n guiados por sus reyes.<\/span><\/p>\n<p class=\"q\"><span class=\"v23_60_12\"><sup id=\"Isa.60.12\" class=\"v23_60_12\">12<\/sup>El pueblo y el reino que no te sirvan<\/span><\/p>\n<p class=\"q\"><span class=\"v23_60_12\">acabar\u00e1n en ruinas, ser\u00e1n desolados.<\/span><\/p>\n<p class=\"q\"><span class=\"v23_60_13\"><sup id=\"Isa.60.13\" class=\"v23_60_13\">13<\/sup>A ti acudir\u00e1 la pompa del L\u00edbano,<\/span><\/p>\n<p class=\"q\"><span class=\"v23_60_13\">cipreses, abetos y pinos juntos,<\/span><\/p>\n<p class=\"q\"><span class=\"v23_60_13\">para dar prestancia a mi santa morada:<\/span><\/p>\n<p class=\"q\"><span class=\"v23_60_13\">as\u00ed honrar\u00e9 el estrado de mis pies.<\/span><\/p>\n<p class=\"q\"><span class=\"v23_60_14\"><sup id=\"Isa.60.14\" class=\"v23_60_14\">14<\/sup>Vendr\u00e1n a ti, humillados,<\/span><\/p>\n<p class=\"q\"><span class=\"v23_60_14\">los hijos de quienes te oprim\u00edan;<\/span><\/p>\n<p class=\"q\"><span class=\"v23_60_14\">te honrar\u00e1n postrados a tus plantas<\/span><\/p>\n<p class=\"q\"><span class=\"v23_60_14\">todos los que te despreciaban;<\/span><\/p>\n<p class=\"q\"><span class=\"v23_60_14\">te llamar\u00e1n Ciudad del Se\u00f1or,<\/span><\/p>\n<p class=\"q\"><span class=\"v23_60_14\">la Si\u00f3n del Santo de Israel.<\/span><\/p>\n<p class=\"q\"><span class=\"v23_60_15\"><sup id=\"Isa.60.15\" class=\"v23_60_15\">15<\/sup>En lugar de estar abandonada,<\/span><\/p>\n<p class=\"q\"><span class=\"v23_60_15\">despreciada, sin habitantes,<\/span><\/p>\n<p class=\"q\"><span class=\"v23_60_15\">te convertir\u00e9 en orgullo de los siglos,<\/span><\/p>\n<p class=\"q\"><span class=\"v23_60_15\">gozo de generaciones y generaciones.<\/span><\/p>\n<p class=\"q\"><span class=\"v23_60_16\"><sup id=\"Isa.60.16\" class=\"v23_60_16\">16<\/sup>Mamar\u00e1s la leche de los pueblos,<\/span><\/p>\n<p class=\"q\"><span class=\"v23_60_16\">mamar\u00e1s de los pechos de reyes,<\/span><\/p>\n<p class=\"q\"><span class=\"v23_60_16\">y sabr\u00e1s que yo, el Se\u00f1or, te salvo;<\/span><\/p>\n<p class=\"q\"><span class=\"v23_60_16\">que tu redentor es el Fuerte de Jacob.<\/span><\/p>\n<p class=\"q\"><span class=\"v23_60_17\"><sup id=\"Isa.60.17\" class=\"v23_60_17\">17<\/sup>En lugar de bronce, te traer\u00e9 oro,<\/span><\/p>\n<p class=\"q\"><span class=\"v23_60_17\">en lugar de hierro, te traer\u00e9 plata,<\/span><\/p>\n<p class=\"q\"><span class=\"v23_60_17\">en lugar de madera, bronce,<\/span><\/p>\n<p class=\"q\"><span class=\"v23_60_17\">y hierro en lugar de piedras.<\/span><\/p>\n<p class=\"q\"><span class=\"v23_60_17\">Te pondr\u00e9 como gobernante la paz,<\/span><\/p>\n<p class=\"q\"><span class=\"v23_60_17\">la justicia ser\u00e1 quien te dirija.<\/span><\/p>\n<p class=\"q\"><span class=\"v23_60_18\"><sup id=\"Isa.60.18\" class=\"v23_60_18\">18<\/sup>Ya no habr\u00e1 violencia en tu tierra,<\/span><\/p>\n<p class=\"q\"><span class=\"v23_60_18\">ni exterminio ni destrucci\u00f3n<\/span><\/p>\n<p class=\"q\"><span class=\"v23_60_18\">dentro de tus fronteras;<\/span><\/p>\n<p class=\"q\"><span class=\"v23_60_18\">llamar\u00e1s a tu muralla \u201cVictoria\u201d<\/span><\/p>\n<p class=\"q\"><span class=\"v23_60_18\">y dir\u00e1s a tus puertas \u201cAlabanza\u201d.<\/span><\/p>\n<p class=\"q\"><span class=\"v23_60_19\"><sup id=\"Isa.60.19\" class=\"v23_60_19\">19<\/sup>Ya no ser\u00e1 el sol tu luz durante el d\u00eda,<\/span><\/p>\n<p class=\"q\"><span class=\"v23_60_19\">ni el resplandor de la luna te alumbrar\u00e1,<\/span><\/p>\n<p class=\"q\"><span class=\"v23_60_19\">pues ser\u00e1 el Se\u00f1or tu luz para siempre,<\/span><\/p>\n<p class=\"q\"><span class=\"v23_60_19\">tu Dios te servir\u00e1 de resplandor;<\/span><\/p>\n<p class=\"q\"><span class=\"v23_60_20\"><sup id=\"Isa.60.20\" class=\"v23_60_20\">20<\/sup>tu sol ya no se pondr\u00e1<\/span><\/p>\n<p class=\"q\"><span class=\"v23_60_20\">y tu luna no menguar\u00e1,<\/span><\/p>\n<p class=\"q\"><span class=\"v23_60_20\">pues ser\u00e1 el Se\u00f1or tu luz para siempre<\/span><\/p>\n<p class=\"q\"><span class=\"v23_60_20\">y se habr\u00e1 cumplido tu tiempo de luto.<\/span><\/p>\n<p class=\"q\"><span class=\"v23_60_21\"><sup id=\"Isa.60.21\" class=\"v23_60_21\">21<\/sup>Todos los de tu pueblo ser\u00e1n justos,<\/span><\/p>\n<p class=\"q\"><span class=\"v23_60_21\">poseer\u00e1n la tierra a perpetuidad:<\/span><\/p>\n<p class=\"q\"><span class=\"v23_60_21\">ellos son el brote que plant\u00e9,<\/span><\/p>\n<p class=\"q\"><span class=\"v23_60_21\">la obra que realic\u00e9 para mi gloria.<\/span><\/p>\n<p class=\"q\"><span class=\"v23_60_22\"><sup id=\"Isa.60.22\" class=\"v23_60_22\">22<\/sup>El peque\u00f1o acabar\u00e1 siendo mil,<\/span><\/p>\n<p class=\"q\"><span class=\"v23_60_22\">el m\u00e1s joven un pueblo potente.<\/span><\/p>\n<p class=\"q\"><span class=\"v23_60_22\">Yo, el Se\u00f1or, no tardar\u00e9<\/span><\/p>\n<p class=\"q\"><span class=\"v23_60_22\">en cumplir todo esto a su tiempo.<\/span><\/p>\n<\/div>\n","chapter":"60","id":"spa-BHTI:Isa.60","osis_end":"spa-BHTI:Isa.60.22","order":"23060","link":"spa-BHTI\/Isa\/60","display":"ISA\u00cdAS 60","book":{"version_id":"173","name":"ISA\u00cdAS","abbr":"Isa","ord":"23","book_group_id":"0","testament":"OT","id":"spa-BHTI:Isa","osis_end":"spa-BHTI:Isa.66.24"},"version":{"auditid":"0","display_abbreviation":"BHTI","version":"spa-BHTI","id":"spa-BHTI","name":"La Biblia Hispanoamericana (Traducci\u00f3n Interconfesional, versi\u00f3n hispanoamericana)","short_desc":null,"description":null,"active":1,"active_api":0,"listed":1,"orderindex":"99","lang":"spa","lang_code":"ISO 639-3","copyright":"<p>La Biblia Hispanoamericana (BHTI) Traducci&#243;n Interconfesional versi&#243;n hispanoamericana Copyright &#169; Sociedad B&#237;blica de Espa&#241;a, 2011 Utilizada con permiso<\/p>","contact_url":"http:\/\/sociedadbiblica.org","audio":"NONE","sections":[{"version_id":"spa-BHTI","id":"OT","name":"Old Testament"},{"version_id":"spa-BHTI","id":"NT","name":"New Testament"}]},"audio":null,"prevChapterId":"spa-BHTI:Isa.59","nextChapterId":"spa-BHTI:Isa.61","footnotes":[],"crossreferences":[]},"footnotes":[],"crossreferences":[]}